pbixray/__init__.py
pbixray/core.py
pbixray/huffman.py
pbixray/pbix_unpacker.py
pbixray/utils.py
pbixray/vertipaq_decoder.py
pbixray/xpress8.py
pbixray/abf/__init__.py
pbixray/abf/backup_log.py
pbixray/abf/backup_log_header.py
pbixray/abf/data_model.py
pbixray/abf/parser.py
pbixray/abf/virtual_directory.py
pbixray/column_data/__init__.py
pbixray/column_data/dictionary.py
pbixray/column_data/hidx.py
pbixray/column_data/idf.py
pbixray/column_data/idfmeta.py
pbixray/meta/__init__.py
pbixray/meta/metadata_handler.py
pbixray/meta/metadata_query.py
pbixray/meta/sqlite_handler.py
pbixray-0.4.0.dist-info/licenses/LICENSE
pbixray-0.4.0.dist-info/METADATA
pbixray-0.4.0.dist-info/WHEEL
pbixray-0.4.0.dist-info/top_level.txt
pbixray-0.4.0.dist-info/RECORD
